undercat/__init__.py
undercat/py.typed
undercat-0.1.2.dist-info/METADATA
undercat-0.1.2.dist-info/WHEEL
undercat-0.1.2.dist-info/licenses/LICENSE
undercat-0.1.2.dist-info/RECORD
