Metadata-Version: 2.4
Name: undercat
Version: 0.1.2
Summary: Library implementing the covariant Hom (AKA "Reader") functor.
Project-URL: Documentation, https://github.com/jeremander/undercat#readme
Project-URL: Issues, https://github.com/jeremander/undercat/issues
Project-URL: Source, https://github.com/jeremander/undercat
Author-email: Jeremy Silver <jeremys@nessiness.com>
License: MIT License
License-File: LICENSE
Classifier: Programming Language :: Python
Requires-Python: >=3.10
